numupi/__init__.py
numupi-0.0.2.dist-info/METADATA
numupi-0.0.2.dist-info/WHEEL
numupi-0.0.2.dist-info/top_level.txt
numupi-0.0.2.dist-info/RECORD
