Metadata-Version: 2.1
Name: numupi
Version: 0.0.2
Summary: hello package
Home-page: UNKNOWN
Author: nandan
Author-email: <nandanpadia@gmail.com>
License: UNKNOWN
Platform: UNKNOWN
